LargeVis/__init__.py
LargeVis-0.0.0.1.dist-info/METADATA
LargeVis-0.0.0.1.dist-info/WHEEL
LargeVis-0.0.0.1.dist-info/top_level.txt
LargeVis-0.0.0.1.dist-info/RECORD
