Metadata-Version: 2.1
Name: LargeVis
Version: 0.0.0.1
Summary: NMF for single cell dataset  .
Home-page: https://github.com/wangzichenbioinformatics/singlecell-NMF
Author: Wangchen
Author-email: wch_bioinformatics@163.com
License: UNKNOWN
Platform: UNKNOWN
Classifier: Programming Language :: Python :: 3
Classifier: License :: OSI Approved :: MIT License
Classifier: Operating System :: OS Independent
Requires-Python: >=3.9
